Disassembled Python bytecode of file "richest_customer_wealth.py", interpreted with Python 3.11:

  0           0 RESUME                   0

 38           2 LOAD_CONST               0 ('accounts')
              4 LOAD_NAME                0 (List)
              6 LOAD_NAME                0 (List)
              8 LOAD_NAME                1 (int)
             10 BINARY_SUBSCR
             20 BINARY_SUBSCR
             30 LOAD_CONST               1 ('return')
             32 LOAD_NAME                1 (int)
             34 BUILD_TUPLE              4
             36 LOAD_CONST               2 (<code object richest_customer_wealth at 0x55fbe4d5de00, file "richest_customer_wealth.py", line 38>)
             38 MAKE_FUNCTION            4 (annotations)
             40 STORE_NAME               2 (richest_customer_wealth)
             42 LOAD_CONST               3 (None)
             44 RETURN_VALUE

Disassembly of <code object richest_customer_wealth at 0x55fbe4d5de00, file "richest_customer_wealth.py", line 38>:

 38           0 RESUME                   0

 39           2 LOAD_GLOBAL              1 (NULL + max)
             14 LOAD_CONST               1 (<code object <genexpr> at 0x55fbe4d5dd00, file "richest_customer_wealth.py", line 39>)
             16 MAKE_FUNCTION            0
             18 LOAD_FAST                1 (accounts)
             20 GET_ITER
             22 PRECALL                  0
             26 CALL                     0
             36 PRECALL                  1
             40 CALL                     1
             50 RETURN_VALUE

Disassembly of <code object <genexpr> at 0x55fbe4d5dd00, file "richest_customer_wealth.py", line 39>:

 39           0 RETURN_GENERATOR
              2 POP_TOP
              4 RESUME                   0
              6 LOAD_FAST                0 (.0)
        >>    8 FOR_ITER                19 (to 48)
             10 STORE_FAST               1 (customer)
             12 LOAD_GLOBAL              1 (NULL + sum)
             24 LOAD_FAST                1 (customer)
             26 PRECALL                  1
             30 CALL                     1
             40 YIELD_VALUE
             42 RESUME                   1
             44 POP_TOP
             46 JUMP_BACKWARD           20 (to 8)
        >>   48 LOAD_CONST               0 (None)
             50 RETURN_VALUE